{
  "$schema": "http://json-schema.org/draft-04/schema#",
  "$ref": "#/definitions/classroom",
  "definitions": {
    "classroom": {
      "type": "object",
      "x-amf-examples": {
        "input": {
          "numberOfClassroom": "AH203"
        },
        "output": {
          "ID": 6,
          "numberOfClassroom": "AH409"
        },
        "example_0": {
          "ID": 1,
          "numberOfClassroom": "AH1B"
        }
      },
      "additionalProperties": true,
      "required": [
        "numberOfClassroom"
      ],
      "properties": {
        "ID": {
          "type": "integer"
        },
        "numberOfClassroom": {
          "type": "string"
        }
      }
    }
  }
}
